main.py
business_bi_mcp-0.1.4.dist-info/licenses/LICENSE
core/__init__.py
core/models.py
core/server.py
tools/__init__.py
tools/core/__init__.py
tools/core/question_analyzer.py
tools/core/sales_analyzer.py
tools/database/__init__.py
tools/database/query_executor.py
tools/database/schema_explorer.py
tools/insights/__init__.py
tools/insights/generator.py
tools/insights/recommender.py
tools/visualization/__init__.py
tools/visualization/chart_advisor.py
business_bi_mcp-0.1.4.dist-info/METADATA
business_bi_mcp-0.1.4.dist-info/WHEEL
business_bi_mcp-0.1.4.dist-info/entry_points.txt
business_bi_mcp-0.1.4.dist-info/top_level.txt
business_bi_mcp-0.1.4.dist-info/RECORD
