Metadata-Version: 2.4
Name: business-bi-mcp
Version: 0.1.4
Summary: 智能BI助手 MCP - 专为业务设计的数据分析MCP，提供7个核心BI分析工具
Author-email: BI MCP Team <contact@business-bi-mcp.com>
Maintainer-email: BI MCP Team <contact@business-bi-mcp.com>
License: MIT
Project-URL: Homepage, https://github.com/business-bi-mcp/business-bi-mcp
Project-URL: Documentation, https://github.com/business-bi-mcp/business-bi-mcp#readme
Project-URL: Repository, https://github.com/business-bi-mcp/business-bi-mcp.git
Project-URL: Issues, https://github.com/business-bi-mcp/business-bi-mcp/issues
Project-URL: Changelog, https://github.com/business-bi-mcp/business-bi-mcp/releases
Project-URL: Bug Reports, https://github.com/business-bi-mcp/business-bi-mcp/issues
Project-URL: Source Code, https://github.com/business-bi-mcp/business-bi-mcp
Keywords: business-intelligence,data-analysis,mcp,business-analytics,non-technical,bi-tools,data-insights,business-decision,chinese,analytics
Classifier: Development Status :: 4 - Beta
Classifier: Intended Audience :: End Users/Desktop
Classifier: Intended Audience :: Developers
Classifier: Intended Audience :: Financial and Insurance Industry
Classifier: Topic :: Office/Business
Classifier: Topic :: Office/Business :: Financial
Classifier: Topic :: Scientific/Engineering :: Information Analysis
Classifier: Topic :: Software Development :: Libraries :: Python Modules
Classifier: License :: OSI Approved :: MIT License
Classifier: Programming Language :: Python :: 3
Classifier: Programming Language :: Python :: 3.12
Classifier: Programming Language :: Python :: 3.13
Classifier: Operating System :: OS Independent
Classifier: Environment :: Console
Classifier: Natural Language :: Chinese (Simplified)
Classifier: Natural Language :: English
Requires-Python: >=3.12
License-File: LICENSE
Requires-Dist: fastmcp>=2.10.1
Requires-Dist: pydantic>=2.0.0
Requires-Dist: httpx>=0.25.0
Requires-Dist: asyncpg>=0.29.0
Requires-Dist: psycopg2-binary>=2.9.0
Provides-Extra: dev
Requires-Dist: pytest>=7.0.0; extra == "dev"
Requires-Dist: black>=22.0.0; extra == "dev"
Requires-Dist: isort>=5.0.0; extra == "dev"
Requires-Dist: mypy>=1.0.0; extra == "dev"
Requires-Dist: ruff>=0.1.0; extra == "dev"
Requires-Dist: build>=0.10.0; extra == "dev"
Requires-Dist: twine>=4.0.0; extra == "dev"
Provides-Extra: test
Requires-Dist: pytest>=7.0.0; extra == "test"
Requires-Dist: pytest-asyncio>=0.21.0; extra == "test"
Requires-Dist: pytest-cov>=4.0.0; extra == "test"
Requires-Dist: coverage>=7.0.0; extra == "test"
Provides-Extra: docs
Requires-Dist: mkdocs>=1.5.0; extra == "docs"
Requires-Dist: mkdocs-material>=9.0.0; extra == "docs"
Requires-Dist: mkdocstrings[python]>=0.22.0; extra == "docs"
Provides-Extra: legacy
Requires-Dist: mcp[cli]>=1.10.1; extra == "legacy"
Requires-Dist: fastapi>=0.104.0; extra == "legacy"
Requires-Dist: uvicorn[standard]>=0.24.0; extra == "legacy"
Dynamic: license-file
